stegosaurus/__init__.py
stegosaurus/example.py
stegosaurus-0.0.1.dist-info/LICENSE
stegosaurus-0.0.1.dist-info/METADATA
stegosaurus-0.0.1.dist-info/WHEEL
stegosaurus-0.0.1.dist-info/top_level.txt
stegosaurus-0.0.1.dist-info/RECORD
