Metadata-Version: 2.1
Name: stegosaurus
Version: 0.0.1
Summary: Fast Image Steganography with numpy - encode a message into a file.
Home-page: https://github.com/xzava/stegosaurus
Author: Mike Hall
Author-email: micheal.hall@gmail.com
License: UNKNOWN
Project-URL: Bug Tracker, https://github.com/xzava/stegosaurus/issues
Platform: UNKNOWN
Classifier: Programming Language :: Python :: 3
Classifier: License :: OSI Approved :: MIT License
Classifier: Operating System :: OS Independent
Requires-Python: >=3.6
License-File: LICENSE
